odoo/addons/stock_picking_product_barcode_report_secondary_unit/README.rst
odoo/addons/stock_picking_product_barcode_report_secondary_unit/__init__.py
odoo/addons/stock_picking_product_barcode_report_secondary_unit/__manifest__.py
odoo/addons/stock_picking_product_barcode_report_secondary_unit/i18n/it.po
odoo/addons/stock_picking_product_barcode_report_secondary_unit/i18n/stock_picking_product_barcode_report_secondary_unit.pot
odoo/addons/stock_picking_product_barcode_report_secondary_unit/readme/CONFIGURE.rst
odoo/addons/stock_picking_product_barcode_report_secondary_unit/readme/CONTRIBUTORS.rst
odoo/addons/stock_picking_product_barcode_report_secondary_unit/readme/DESCRIPTION.rst
odoo/addons/stock_picking_product_barcode_report_secondary_unit/static/description/icon.png
odoo/addons/stock_picking_product_barcode_report_secondary_unit/static/description/index.html
odoo/addons/stock_picking_product_barcode_report_secondary_unit/tests/__init__.py
odoo/addons/stock_picking_product_barcode_report_secondary_unit/tests/test_stock_picking_product_barcode_report_secondary_unit.py
odoo/addons/stock_picking_product_barcode_report_secondary_unit/wizard/__init__.py
odoo/addons/stock_picking_product_barcode_report_secondary_unit/wizard/stock_barcode_selection_printing.py
odoo_addon_stock_picking_product_barcode_report_secondary_unit-16.0.1.0.0.3.dist-info/METADATA
odoo_addon_stock_picking_product_barcode_report_secondary_unit-16.0.1.0.0.3.dist-info/WHEEL
odoo_addon_stock_picking_product_barcode_report_secondary_unit-16.0.1.0.0.3.dist-info/top_level.txt
odoo_addon_stock_picking_product_barcode_report_secondary_unit-16.0.1.0.0.3.dist-info/RECORD
