Metadata-Version: 2.1
Name: odoo-addon-stock_picking_product_barcode_report_secondary_unit
Version: 16.0.1.0.0.3
Summary: Set by default the maximum quantity of labels to print.
Home-page: https://github.com/OCA/stock-logistics-barcode
Author: Tecnativa, Odoo Community Association (OCA)
Author-email: support@odoo-community.org
License: AGPL-3
Classifier: Programming Language :: Python
Classifier: Framework :: Odoo
Classifier: Framework :: Odoo :: 16.0
Classifier: License :: OSI Approved :: GNU Affero General Public License v3
Requires-Python: >=3.10
Requires-Dist: odoo-addon-stock-picking-product-barcode-report<16.1dev,>=16.0dev
Requires-Dist: odoo-addon-stock-secondary-unit<16.1dev,>=16.0dev
Requires-Dist: odoo<16.1dev,>=16.0a
Requires-Dist: python-barcode
